voxelobj/__init__.py
voxelobj/core.py
voxelobj-0.0.1.dist-info/LICENSE
voxelobj-0.0.1.dist-info/METADATA
voxelobj-0.0.1.dist-info/WHEEL
voxelobj-0.0.1.dist-info/top_level.txt
voxelobj-0.0.1.dist-info/RECORD
