Metadata-Version: 2.1
Name: voxelobj
Version: 0.0.1
Summary: simple voxel library
Home-page: https://github.com/martinpflaum/voxel_obj_lib_in_python
Author: Martin Pflaum
Author-email: martin.pflaum.09.03.1999@gmail.com
License: UNKNOWN
Project-URL: Bug Tracker, https://github.com/martinpflaum/voxel_obj_lib_in_python/issues
Keywords: python,voxel,obj,3D
Platform: UNKNOWN
Classifier: Programming Language :: Python :: 3
Classifier: License :: OSI Approved :: MIT License
Classifier: Operating System :: OS Independent
Requires-Python: >=3.6
Requires-Dist: numpy
